se3_transformer_pytorch/__init__.py
se3_transformer_pytorch/basis.py
se3_transformer_pytorch/irr_repr.py
se3_transformer_pytorch/reversible.py
se3_transformer_pytorch/rotary.py
se3_transformer_pytorch/se3_transformer_pytorch.py
se3_transformer_pytorch/spherical_harmonics.py
se3_transformer_pytorch/utils.py
se3_transformer_pytorch/data/J_dense.npy
se3_transformer_pytorch/data/J_dense.pt
se3_transformer_pytorch-0.9.0.dist-info/LICENSE
se3_transformer_pytorch-0.9.0.dist-info/METADATA
se3_transformer_pytorch-0.9.0.dist-info/WHEEL
se3_transformer_pytorch-0.9.0.dist-info/top_level.txt
se3_transformer_pytorch-0.9.0.dist-info/RECORD
