Metadata-Version: 2.1
Name: se3-transformer-pytorch
Version: 0.9.0
Summary: SE3 Transformer - Pytorch
Home-page: https://github.com/lucidrains/se3-transformer-pytorch
Author: Phil Wang
Author-email: lucidrains@gmail.com
License: MIT
Keywords: artificial intelligence,attention mechanism,transformers,equivariance,SE3
Classifier: Development Status :: 4 - Beta
Classifier: Intended Audience :: Developers
Classifier: Topic :: Scientific/Engineering :: Artificial Intelligence
Classifier: License :: OSI Approved :: MIT License
Classifier: Programming Language :: Python :: 3.6
License-File: LICENSE
Requires-Dist: einops (>=0.3)
Requires-Dist: filelock
Requires-Dist: numpy
Requires-Dist: torch (>=1.6)
